hankdong_weather_service/__init__.py
hankdong_weather_service/weather.py
hankdong_weather_service-0.1.0.dist-info/METADATA
hankdong_weather_service-0.1.0.dist-info/WHEEL
hankdong_weather_service-0.1.0.dist-info/licenses/LICENSE
hankdong_weather_service-0.1.0.dist-info/RECORD
