Metadata-Version: 2.4
Name: hankdong-weather-service
Version: 0.1.0
Summary: A Python package for accessing weather data from NWS API
Project-URL: Homepage, https://github.com/jianghaobai/weather-service
Project-URL: Bug Tracker, https://github.com/jianghaobai/weather-service/issues
Author-email: hankdong <hankdong2019@gmail.com>
License-File: LICENSE
Classifier: License :: OSI Approved :: MIT License
Classifier: Operating System :: OS Independent
Classifier: Programming Language :: Python :: 3
Requires-Python: >=3.8
Requires-Dist: httpx>=0.24.0
Requires-Dist: mcp-server>=0.1.0
